robojslib/__init__.py
robojslib/drivers.py
robojslib/keywords.py
robojslib/robojslib.py
robojslib/version.py
robojslib/version1.py
robojslib-0.3.8.dist-info/LICENSE
robojslib-0.3.8.dist-info/METADATA
robojslib-0.3.8.dist-info/WHEEL
robojslib-0.3.8.dist-info/top_level.txt
robojslib-0.3.8.dist-info/RECORD
