Metadata-Version: 2.1
Name: robojslib
Version: 0.3.8
Summary: A simple RobotFramework keyword library written using Vanilla/Python
Home-page: https://github.com/andreagubellini/RoboJSLib
Author: Andrea Gubellini
Author-email: agubellini@yahoo.com
License: UNKNOWN
Platform: UNKNOWN
Classifier: Programming Language :: Python :: 3
Classifier: License :: OSI Approved :: MIT License
Classifier: Operating System :: OS Independent
Requires-Dist: robotframework
Requires-Dist: robotframework-seleniumlibrary
